grain/__init__.py
grain/checkpoint.py
grain/constants.py
grain/experimental.py
grain/multiprocessing.py
grain/samplers.py
grain/sharding.py
grain/sources.py
grain/transforms.py
grain/_src/__init__.py
grain/_src/core/config.py
grain/_src/core/constants.py
grain/_src/core/exceptions.py
grain/_src/core/grain_random.py
grain/_src/core/jax_import_smoke_test.py
grain/_src/core/monitoring.py
grain/_src/core/parallel.py
grain/_src/core/parallel_test.py
grain/_src/core/py_version_test.py
grain/_src/core/sharding.py
grain/_src/core/sharding_test.py
grain/_src/core/tf_import_smoke_test.py
grain/_src/core/transforms.py
grain/_src/core/transforms_test.py
grain/_src/core/tree_lib.py
grain/_src/core/tree_lib_jax_test.py
grain/_src/core/tree_lib_test.py
grain/_src/core/usage_logging.py
grain/_src/core/version.py
grain/_src/python/checkpoint_handlers.py
grain/_src/python/checkpointing.py
grain/_src/python/data_loader.py
grain/_src/python/data_loader_test.py
grain/_src/python/data_sources.py
grain/_src/python/data_sources_test.py
grain/_src/python/grain_logging.py
grain/_src/python/grain_logging_test.py
grain/_src/python/grain_pool.py
grain/_src/python/grain_pool_test.py
grain/_src/python/load.py
grain/_src/python/load_test.py
grain/_src/python/multiprocessing_common.py
grain/_src/python/multiprocessing_common_test.py
grain/_src/python/operations.py
grain/_src/python/operations_test.py
grain/_src/python/options.py
grain/_src/python/options_test.py
grain/_src/python/record.py
grain/_src/python/record_test.py
grain/_src/python/samplers.py
grain/_src/python/samplers_test.py
grain/_src/python/shared_memory_array.py
grain/_src/python/shared_memory_array_test.py
grain/_src/python/dataset/base.py
grain/_src/python/dataset/base_test.py
grain/_src/python/dataset/dataset.py
grain/_src/python/dataset/dataset_test.py
grain/_src/python/dataset/elastic_iterator.py
grain/_src/python/dataset/elastic_iterator_test.py
grain/_src/python/dataset/stats.py
grain/_src/python/dataset/stats_test.py
grain-0.2.13.dist-info/licenses/LICENSE
grain-0.2.13.dist-info/METADATA
grain-0.2.13.dist-info/WHEEL
grain-0.2.13.dist-info/top_level.txt
grain-0.2.13.dist-info/RECORD
